{
  "componentList": [],
  "directiveList": [
    {
      "name": "LyBadge",
      "selector": "<div class=\"ttb\"><pre class=\"ttm\"><span class=\"tt18 tt3z\">'ly-badge, [lyBadge]'</span></pre></div>",
      "inputs": "<div class=\"ttb\"><pre class=\"ttm\"><span class=\"tt18 ttae\">[</span>\n  <span class=\"tt18 tt3z\">\"bg\"</span><span class=\"tt18 ttae\">,</span>\n  <span class=\"tt18 tt3z\">\"color\"</span><span class=\"tt18 ttae\">,</span>\n  <span class=\"tt18 tt3z\">\"raised\"</span><span class=\"tt18 ttae\">,</span>\n  <span class=\"tt18 tt3z\">\"disabled\"</span><span class=\"tt18 ttae\">,</span>\n  <span class=\"tt18 tt3z\">\"outlined\"</span><span class=\"tt18 ttae\">,</span>\n  <span class=\"tt18 tt3z\">\"elevation\"</span><span class=\"tt18 ttae\">,</span>\n  <span class=\"tt18 tt3z\">\"shadowColor\"</span>\n<span class=\"tt18 ttae\">]</span></pre></div>",
      "exportAs": "",
      "children": "<div class=\"ttb\"><pre class=\"ttm\"><span class=\"tt18 tt3o\">/** The content for the badge */</span>\n@<span class=\"tt18 tta3\">Input</span><span class=\"tt18 ttae\">(</span><span class=\"tt18 tt3z\">'lyBadge'</span><span class=\"tt18 ttae\">)</span> content<span class=\"tt18 ttae\">:</span> <span class=\"tt18 ttcj\">string</span> <span class=\"tt18 ttb0\">|</span> <span class=\"tt18 ttcj\">number</span>\n<span class=\"tt18 tt3o\">/** The color of the badge */</span>\n@<span class=\"tt18 tta3\">Input</span><span class=\"tt18 ttae\">(</span><span class=\"tt18 ttae\">)</span> lyBadgeBg<span class=\"tt18 ttae\">:</span> <span class=\"tt18 ttcj\">string</span>\n<span class=\"tt18 tt3o\">/** The position for the badge */</span>\n@<span class=\"tt18 tta3\">Input</span><span class=\"tt18 ttae\">(</span><span class=\"tt18 tt3z\">'lyBadgePosition'</span><span class=\"tt18 ttae\">)</span> position<span class=\"tt18 ttae\">:</span> <span class=\"tt18 ttcj\">string</span></pre></div>"
    }
  ],
  "variableList": [
    {
      "name": "DEFAULT_BG",
      "children": "<div class=\"ttb\"><pre class=\"ttm\"><span class=\"tt18 tt1j\">const</span> <span class=\"tt18 ttbb\">DEFAULT_BG</span> <span class=\"tt18 ttb0\">=</span> <span class=\"tt18 tt3z\">\"primary\"</span></pre></div>"
    },
    {
      "name": "DEFAULT_POSITION",
      "children": "<div class=\"ttb\"><pre class=\"ttm\"><span class=\"tt18 tt1j\">const</span> <span class=\"tt18 ttbb\">DEFAULT_POSITION</span> <span class=\"tt18 ttb0\">=</span> <span class=\"tt18 tt3z\">\"startTop\"</span></pre></div>"
    },
    {
      "name": "STYLE_PRIORITY",
      "children": "<div class=\"ttb\"><pre class=\"ttm\"><span class=\"tt18 tt1j\">const</span> <span class=\"tt18 ttbb\">STYLE_PRIORITY</span> <span class=\"tt18 ttb0\">=</span> <span class=\"tt18 ttb0\">-</span><span class=\"tt18 ttap\">2</span></pre></div>"
    }
  ],
  "ngModuleList": [
    {
      "name": "LyBadgeModule",
      "children": "<div class=\"ttb\"><pre class=\"ttm\"><span class=\"tt18 tt1j\">import</span> <span class=\"tt18 ttae\">&#123;</span> LyBadgeModule <span class=\"tt18 ttae\">&#125;</span> <span class=\"tt18 tt1j\">from</span> <span class=\"tt18 tt3z\">'@alyle/ui/badge'</span></pre></div>"
    }
  ]
}